docstrap/__init__.py
docstrap/cli.py
docstrap/config/__init__.py
docstrap/config/loader.py
docstrap/config/models.py
docstrap/config/template.py
docstrap/core/__init__.py
docstrap/core/formatter.py
docstrap/core/manager.py
docstrap/core/mkdocs.py
docstrap/fs/__init__.py
docstrap/fs/handler.py
docstrap/fs/migrator.py
docstrap/utils/__init__.py
docstrap/utils/logging.py
docstrap-0.1.2.dist-info/LICENSE.md
docstrap-0.1.2.dist-info/METADATA
docstrap-0.1.2.dist-info/WHEEL
docstrap-0.1.2.dist-info/entry_points.txt
docstrap-0.1.2.dist-info/RECORD
