Metadata-Version: 2.1
Name: docstrap
Version: 0.1.2
Summary: A tool for bootstrapping and managing documentation project structures
Home-page: https://github.com/tjcunliffe/docstrap
License: MIT
Keywords: documentation,bootstrap,scaffold,structure,generator
Author: Tom Cunliffe
Author-email: tom.cunliffe@onoclea.io
Requires-Python: >=3.9,<4.0
Classifier: Development Status :: 3 - Alpha
Classifier: Environment :: Console
Classifier: Intended Audience :: Developers
Classifier: License :: OSI Approved :: MIT License
Classifier: Operating System :: OS Independent
Classifier: Programming Language :: Python :: 3
Classifier: Programming Language :: Python :: 3.9
Classifier: Programming Language :: Python :: 3.10
Classifier: Programming Language :: Python :: 3.11
Classifier: Programming Language :: Python :: 3.12
Classifier: Programming Language :: Python :: 3.13
Classifier: Topic :: Documentation
Classifier: Topic :: Software Development :: Documentation
Classifier: Topic :: Software Development :: Libraries :: Python Modules
Classifier: Typing :: Typed
Requires-Dist: poetry (>=1.8.4,<2.0.0)
Requires-Dist: pyyaml (>=6.0.1,<7.0.0)
Requires-Dist: types-PyYAML (>=6.0.12.12,<7.0.0.0)
Project-URL: Documentation, https://github.com/tjcunliffe/docstrap
Project-URL: Repository, https://github.com/tjcunliffe/docstrap
